docs/conf.py
sleepeegpy/base.py
sleepeegpy/dashboard.py
sleepeegpy/pipeline.py
sleepeegpy/utils.py
sleepeegpy-0.6.0.dist-info/LICENSE
sleepeegpy-0.6.0.dist-info/METADATA
sleepeegpy-0.6.0.dist-info/WHEEL
sleepeegpy-0.6.0.dist-info/top_level.txt
sleepeegpy-0.6.0.dist-info/RECORD
