Metadata-Version: 2.1
Name: sleepeegpy
Version: 0.6.0
Summary: Sleep EEG preprocessing, analysis and visualization
Author-email: Gennadiy Belonosov <gennadiyb@mail.tau.ac.il>, Rotem Falach <rotemfalach@mail.tau.ac.il>
License: MIT
Project-URL: Homepage, https://github.com/NirLab-TAU/sleepeegpy
Project-URL: Documentation, https://nirlab-tau.github.io/sleepeegpy/
Keywords: sleep,eeg
Requires-Python: <3.12,>=3.10
License-File: LICENSE
Requires-Dist: attrs
Requires-Dist: mne ~=1.6.0
Requires-Dist: mne-qt-browser
Requires-Dist: pyqt5
Requires-Dist: yasa ~=0.6.3
Requires-Dist: fooof ~=1.1.0
Requires-Dist: lspopt
Requires-Dist: ipympl
Requires-Dist: numpy ~=1.25.2
Requires-Dist: pandas
Requires-Dist: matplotlib ~=3.8.0
Requires-Dist: scipy
Requires-Dist: natsort
Requires-Dist: more-itertools
Requires-Dist: h5io
Requires-Dist: loguru
Requires-Dist: pooch
Requires-Dist: tqdm
Requires-Dist: pyprep ~=0.4.3
Requires-Dist: ipywidgets
Requires-Dist: ipython
